JiucaiDeZiwoXiuyang/README.md
JiucaiDeZiwoXiuyang/__init__.py
JiucaiDeZiwoXiuyang/__main__.py
JiucaiDeZiwoXiuyang/file.epub
JiucaiDeZiwoXiuyang/index.html
JiucaiDeZiwoXiuyang/css/__init__.py
JiucaiDeZiwoXiuyang/css/annotations.css
JiucaiDeZiwoXiuyang/css/main.css
JiucaiDeZiwoXiuyang/css/normalize.css
JiucaiDeZiwoXiuyang/css/popup.css
JiucaiDeZiwoXiuyang/font/__init__.py
JiucaiDeZiwoXiuyang/font/fontello.eot
JiucaiDeZiwoXiuyang/font/fontello.svg
JiucaiDeZiwoXiuyang/font/fontello.ttf
JiucaiDeZiwoXiuyang/font/fontello.woff
JiucaiDeZiwoXiuyang/img/__init__.py
JiucaiDeZiwoXiuyang/img/annotator-glyph-sprite.png
JiucaiDeZiwoXiuyang/img/annotator-icon-sprite.png
JiucaiDeZiwoXiuyang/img/apple-touch-icon.png
JiucaiDeZiwoXiuyang/img/cancelfullscreen.png
JiucaiDeZiwoXiuyang/img/close.png
JiucaiDeZiwoXiuyang/img/fullscreen.png
JiucaiDeZiwoXiuyang/img/loader.gif
JiucaiDeZiwoXiuyang/img/menu-icon.png
JiucaiDeZiwoXiuyang/img/save.png
JiucaiDeZiwoXiuyang/img/saved.png
JiucaiDeZiwoXiuyang/img/settings-s.png
JiucaiDeZiwoXiuyang/img/settings.png
JiucaiDeZiwoXiuyang/img/star.png
JiucaiDeZiwoXiuyang/js/__init__.py
JiucaiDeZiwoXiuyang/js/epub.js
JiucaiDeZiwoXiuyang/js/epub.min.js
JiucaiDeZiwoXiuyang/js/epub.min.map
JiucaiDeZiwoXiuyang/js/hooks.min.js
JiucaiDeZiwoXiuyang/js/hooks.min.map
JiucaiDeZiwoXiuyang/js/reader.js
JiucaiDeZiwoXiuyang/js/reader.js.map
JiucaiDeZiwoXiuyang/js/reader.min.js
JiucaiDeZiwoXiuyang/js/reader.min.map
JiucaiDeZiwoXiuyang/js/hooks/__init__.py
JiucaiDeZiwoXiuyang/js/hooks/extensions/__init__.py
JiucaiDeZiwoXiuyang/js/hooks/extensions/highlight.js
JiucaiDeZiwoXiuyang/js/libs/__init__.py
JiucaiDeZiwoXiuyang/js/libs/jquery.min.js
JiucaiDeZiwoXiuyang/js/libs/localforage.min.js
JiucaiDeZiwoXiuyang/js/libs/screenfull.js
JiucaiDeZiwoXiuyang/js/libs/screenfull.min.js
JiucaiDeZiwoXiuyang/js/libs/zip.min.js
JiucaiDeZiwoXiuyang/js/plugins/__init__.py
JiucaiDeZiwoXiuyang/js/plugins/hypothesis.js
JiucaiDeZiwoXiuyang/js/plugins/search.js
jiucai_de_ziwo_xiuyang-2024.3.4.0.dist-info/METADATA
jiucai_de_ziwo_xiuyang-2024.3.4.0.dist-info/WHEEL
jiucai_de_ziwo_xiuyang-2024.3.4.0.dist-info/entry_points.txt
jiucai_de_ziwo_xiuyang-2024.3.4.0.dist-info/top_level.txt
jiucai_de_ziwo_xiuyang-2024.3.4.0.dist-info/RECORD
